qemu_discord_rpc/__init__.py
qemu_discord_rpc-1.0.3.dist-info/licenses/LICENSE
qemu_discord_rpc-1.0.3.dist-info/METADATA
qemu_discord_rpc-1.0.3.dist-info/WHEEL
qemu_discord_rpc-1.0.3.dist-info/entry_points.txt
qemu_discord_rpc-1.0.3.dist-info/top_level.txt
qemu_discord_rpc-1.0.3.dist-info/RECORD
