Metadata-Version: 2.4
Name: qemu-discord-rpc
Version: 1.0.3
Summary: Display running QEMU virtual machines as Discord Rich Presence status
Author-email: qubixq <83471324+qubixq@users.noreply.github.com>
License: GPL-3.0
Project-URL: Homepage, https://github.com/qubixq/qemu-discord-rpc
Project-URL: Bug Reports, https://github.com/qubixq/qemu-discord-rpc/issues
Project-URL: Source, https://github.com/qubixq/qemu-discord-rpc
Project-URL: Documentation, https://github.com/qubixq/qemu-discord-rpc#readme
Keywords: qemu,discord,rpc,virtual-machine,status,rich-presence
Classifier: Development Status :: 4 - Beta
Classifier: Intended Audience :: Developers
Classifier: Intended Audience :: End Users/Desktop
Classifier: License :: OSI Approved :: GNU General Public License v3 (GPLv3)
Classifier: Operating System :: POSIX :: Linux
Classifier: Operating System :: Unix
Classifier: Programming Language :: Python :: 3
Classifier: Programming Language :: Python :: 3.6
Classifier: Programming Language :: Python :: 3.7
Classifier: Programming Language :: Python :: 3.8
Classifier: Programming Language :: Python :: 3.9
Classifier: Programming Language :: Python :: 3.10
Classifier: Programming Language :: Python :: 3.11
Classifier: Programming Language :: Python :: 3.12
Classifier: Topic :: System :: Emulators
Classifier: Topic :: Communications :: Chat
Classifier: Topic :: Utilities
Classifier: Topic :: Games/Entertainment
Requires-Python: >=3.6
License-File: LICENSE
Requires-Dist: pypresence>=4.0.0
Provides-Extra: dev
Requires-Dist: build; extra == "dev"
Requires-Dist: twine; extra == "dev"
Requires-Dist: pytest; extra == "dev"
Requires-Dist: black; extra == "dev"
Requires-Dist: flake8; extra == "dev"
Dynamic: license-file
